{
    "ticker": "CAPO",
    "epochs": [
        {
            "epoch": 260,
            "expected": 0.0,
            "actual": 0,
            "pool_stake": 1007622138,
            "total_stake": 22796009141134396,
            "decentralisation_coefficient": 0,
            "slot_coefficient": 0.05,
            "cumulative_expected_blocks": 0,
            "cumulative_actual_blocks": 0,
            "epoch_diff": 0,
            "epoch_cumulative_diff": 0
        },
        {
            "epoch": 261,
            "expected": 0.21,
            "actual": 1,
            "pool_stake": 219388345661,
            "total_stake": 22716225550169723,
            "decentralisation_coefficient": 0,
            "slot_coefficient": 0.05,
            "cumulative_expected_blocks": 0.2099999999999999922284388276,
            "cumulative_actual_blocks": 1,
            "epoch_diff": 0.7900000000000000077715611724,
            "epoch_cumulative_diff": 0.7900000000000000077715611724
        },
        {
            "epoch": 262,
            "expected": 0.21,
            "actual": 0,
            "pool_stake": 219956241249,
            "total_stake": 22755688720340301,
            "decentralisation_coefficient": 0,
            "slot_coefficient": 0.05,
            "cumulative_expected_blocks": 0.4199999999999999844568776552,
            "cumulative_actual_blocks": 1,
            "epoch_diff": -0.2099999999999999922284388276,
            "epoch_cumulative_diff": 0.5800000000000000155431223448
        },
        {
            "epoch": 263,
            "expected": 0.21,
            "actual": 0,
            "pool_stake": 220135072996,
            "total_stake": 22726917708873365,
            "decentralisation_coefficient": 0,
            "slot_coefficient": 0.05,
            "cumulative_expected_blocks": 0.6299999999999999766853164828,
            "cumulative_actual_blocks": 1,
            "epoch_diff": -0.2099999999999999922284388276,
            "epoch_cumulative_diff": 0.3700000000000000233146835172
        },
        {
            "epoch": 264,
            "expected": 0.23,
            "actual": 0,
            "pool_stake": 242082989593,
            "total_stake": 22955953661896809,
            "decentralisation_coefficient": 0,
            "slot_coefficient": 0.05,
            "cumulative_expected_blocks": 0.8599999999999999866773237044,
            "cumulative_actual_blocks": 1,
            "epoch_diff": -0.2300000000000000099920072216,
            "epoch_cumulative_diff": 0.1400000000000000133226762956
        },
        {
            "epoch": 265,
            "expected": 0.44,
            "actual": 1,
            "pool_stake": 464665970698,
            "total_stake": 23026399223411517,
            "decentralisation_coefficient": 0,
            "slot_coefficient": 0.05,
            "cumulative_expected_blocks": 1.299999999999999988897769754,
            "cumulative_actual_blocks": 2,
            "epoch_diff": 0.5599999999999999977795539507,
            "epoch_cumulative_diff": 0.7000000000000000111022302463
        },
        {
            "epoch": 266,
            "expected": 0.44,
            "actual": 1,
            "pool_stake": 469408505530,
            "total_stake": 23083634214117687,
            "decentralisation_coefficient": 0,
            "slot_coefficient": 0.05,
            "cumulative_expected_blocks": 1.739999999999999991118215803,
            "cumulative_actual_blocks": 3,
            "epoch_diff": 0.5599999999999999977795539507,
            "epoch_cumulative_diff": 1.260000000000000008881784197
        },
        {
            "epoch": 267,
            "expected": 0.25,
            "actual": 1,
            "pool_stake": 270813209468,
            "total_stake": 23021654510419471,
            "decentralisation_coefficient": 0,
            "slot_coefficient": 0.05,
            "cumulative_expected_blocks": 1.989999999999999991118215803,
            "cumulative_actual_blocks": 4,
            "epoch_diff": 0.75,
            "epoch_cumulative_diff": 2.010000000000000008881784197
        },
        {
            "epoch": 268,
            "expected": 0.32,
            "actual": 0,
            "pool_stake": 342710938725,
            "total_stake": 22843314790026736,
            "decentralisation_coefficient": 0,
            "slot_coefficient": 0.05,
            "cumulative_expected_blocks": 2.309999999999999997779553951,
            "cumulative_actual_blocks": 4,
            "epoch_diff": -0.3200000000000000066613381478,
            "epoch_cumulative_diff": 1.690000000000000002220446049
        },
        {
            "epoch": 269,
            "expected": 0.32,
            "actual": 0,
            "pool_stake": 340409669498,
            "total_stake": 22786770256604950,
            "decentralisation_coefficient": 0,
            "slot_coefficient": 0.05,
            "cumulative_expected_blocks": 2.630000000000000004440892099,
            "cumulative_actual_blocks": 4,
            "epoch_diff": -0.3200000000000000066613381478,
            "epoch_cumulative_diff": 1.369999999999999995559107901
        },
        {
            "epoch": 270,
            "expected": 0.34,
            "actual": 0,
            "pool_stake": 356492499533,
            "total_stake": 22893778548073522,
            "decentralisation_coefficient": 0,
            "slot_coefficient": 0.05,
            "cumulative_expected_blocks": 2.970000000000000028865798641,
            "cumulative_actual_blocks": 4,
            "epoch_diff": -0.3400000000000000244249065418,
            "epoch_cumulative_diff": 1.029999999999999971134201359
        },
        {
            "epoch": 271,
            "expected": 0.34,
            "actual": 1,
            "pool_stake": 360238993207,
            "total_stake": 22970909569111347,
            "decentralisation_coefficient": 0,
            "slot_coefficient": 0.05,
            "cumulative_expected_blocks": 3.310000000000000053290705183,
            "cumulative_actual_blocks": 5,
            "epoch_diff": 0.6599999999999999755750934582,
            "epoch_cumulative_diff": 1.689999999999999946709294817
        },
        {
            "epoch": 272,
            "expected": 0.35,
            "actual": 0,
            "pool_stake": 372685744931,
            "total_stake": 23020000415780615,
            "decentralisation_coefficient": 0,
            "slot_coefficient": 0.05,
            "cumulative_expected_blocks": 3.660000000000000031086244690,
            "cumulative_actual_blocks": 5,
            "epoch_diff": -0.3499999999999999777955395075,
            "epoch_cumulative_diff": 1.339999999999999968913755310
        },
        {
            "epoch": 273,
            "expected": 0.36,
            "actual": 0,
            "pool_stake": 384545185746,
            "total_stake": 23075664958746578,
            "decentralisation_coefficient": 0,
            "slot_coefficient": 0.05,
            "cumulative_expected_blocks": 4.020000000000000017763568394,
            "cumulative_actual_blocks": 5,
            "epoch_diff": -0.3599999999999999866773237045,
            "epoch_cumulative_diff": 0.9799999999999999822364316055
        },
        {
            "epoch": 274,
            "expected": 0.38,
            "actual": 0,
            "pool_stake": 404059896013,
            "total_stake": 23094302016775953,
            "decentralisation_coefficient": 0,
            "slot_coefficient": 0.05,
            "cumulative_expected_blocks": 4.400000000000000022204460493,
            "cumulative_actual_blocks": 5,
            "epoch_diff": -0.3800000000000000044408920985,
            "epoch_cumulative_diff": 0.5999999999999999777955395070
        },
        {
            "epoch": 275,
            "expected": 0.41,
            "actual": 0,
            "pool_stake": 432927812571,
            "total_stake": 23006172979540278,
            "decentralisation_coefficient": 0,
            "slot_coefficient": 0.05,
            "cumulative_expected_blocks": 4.809999999999999997779553951,
            "cumulative_actual_blocks": 5,
            "epoch_diff": -0.4099999999999999755750934582,
            "epoch_cumulative_diff": 0.1900000000000000022204460488
        },
        {
            "epoch": 276,
            "expected": 0.41,
            "actual": 0,
            "pool_stake": 439324462321,
            "total_stake": 23092420021153886,
            "decentralisation_coefficient": 0,
            "slot_coefficient": 0.05,
            "cumulative_expected_blocks": 5.219999999999999973354647409,
            "cumulative_actual_blocks": 5,
            "epoch_diff": -0.4099999999999999755750934582,
            "epoch_cumulative_diff": -0.2199999999999999733546474094
        },
        {
            "epoch": 277,
            "expected": 0.41,
            "actual": 0,
            "pool_stake": 444947856470,
            "total_stake": 23196615273348567,
            "decentralisation_coefficient": 0,
            "slot_coefficient": 0.05,
            "cumulative_expected_blocks": 5.629999999999999948929740867,
            "cumulative_actual_blocks": 5,
            "epoch_diff": -0.4099999999999999755750934582,
            "epoch_cumulative_diff": -0.6299999999999999489297408676
        },
        {
            "epoch": 278,
            "expected": 0.43,
            "actual": 0,
            "pool_stake": 463537213083,
            "total_stake": 23196379717228316,
            "decentralisation_coefficient": 0,
            "slot_coefficient": 0.05,
            "cumulative_expected_blocks": 6.059999999999999942268402719,
            "cumulative_actual_blocks": 5,
            "epoch_diff": -0.4299999999999999933386618522,
            "epoch_cumulative_diff": -1.059999999999999942268402720
        },
        {
            "epoch": 279,
            "expected": 0.55,
            "actual": 0,
            "pool_stake": 585708123068,
            "total_stake": 23210733595257321,
            "decentralisation_coefficient": 0,
            "slot_coefficient": 0.05,
            "cumulative_expected_blocks": 6.609999999999999986677323704,
            "cumulative_actual_blocks": 5,
            "epoch_diff": -0.5500000000000000444089209850,
            "epoch_cumulative_diff": -1.609999999999999986677323705
        },
        {
            "epoch": 280,
            "expected": 0.53,
            "actual": 0,
            "pool_stake": 565975122611,
            "total_stake": 23230827525683631,
            "decentralisation_coefficient": 0,
            "slot_coefficient": 0.05,
            "cumulative_expected_blocks": 7.140000000000000013322676295,
            "cumulative_actual_blocks": 5,
            "epoch_diff": -0.5300000000000000266453525910,
            "epoch_cumulative_diff": -2.140000000000000013322676296
        },
        {
            "epoch": 281,
            "expected": 0.53,
            "actual": 0,
            "pool_stake": 569778816808,
            "total_stake": 23254470605645231,
            "decentralisation_coefficient": 0,
            "slot_coefficient": 0.05,
            "cumulative_expected_blocks": 7.670000000000000039968028886,
            "cumulative_actual_blocks": 5,
            "epoch_diff": -0.5300000000000000266453525910,
            "epoch_cumulative_diff": -2.670000000000000039968028887
        },
        {
            "epoch": 282,
            "expected": 0.56,
            "actual": 0,
            "pool_stake": 602029530096,
            "total_stake": 23244660857359753,
            "decentralisation_coefficient": 0,
            "slot_coefficient": 0.05,
            "cumulative_expected_blocks": 8.230000000000000093258734068,
            "cumulative_actual_blocks": 5,
            "epoch_diff": -0.5600000000000000532907051820,
            "epoch_cumulative_diff": -3.230000000000000093258734069
        },
        {
            "epoch": 283,
            "expected": 0.59,
            "actual": 0,
            "pool_stake": 633772489135,
            "total_stake": 23277148789435534,
            "decentralisation_coefficient": 0,
            "slot_coefficient": 0.05,
            "cumulative_expected_blocks": 8.820000000000000062172489378,
            "cumulative_actual_blocks": 5,
            "epoch_diff": -0.5899999999999999689137553105,
            "epoch_cumulative_diff": -3.820000000000000062172489380
        },
        {
            "epoch": 284,
            "expected": 0.59,
            "actual": 1,
            "pool_stake": 639527775165,
            "total_stake": 23275724668511213,
            "decentralisation_coefficient": 0,
            "slot_coefficient": 0.05,
            "cumulative_expected_blocks": 9.410000000000000031086244688,
            "cumulative_actual_blocks": 6,
            "epoch_diff": 0.4100000000000000310862446895,
            "epoch_cumulative_diff": -3.410000000000000031086244690
        },
        {
            "epoch": 285,
            "expected": 0.59,
            "actual": 0,
            "pool_stake": 628811415932,
            "total_stake": 23159940155010115,
            "decentralisation_coefficient": 0,
            "slot_coefficient": 0.05,
            "cumulative_expected_blocks": 9.999999999999999999999999998,
            "cumulative_actual_blocks": 6,
            "epoch_diff": -0.5899999999999999689137553105,
            "epoch_cumulative_diff": -4.000000000000000000000000000
        },
        {
            "epoch": 286,
            "expected": 0.57,
            "actual": 0,
            "pool_stake": 607752285733,
            "total_stake": 23141094607453731,
            "decentralisation_coefficient": 0,
            "slot_coefficient": 0.05,
            "cumulative_expected_blocks": 10.56999999999999995115018691,
            "cumulative_actual_blocks": 6,
            "epoch_diff": -0.5699999999999999511501869165,
            "epoch_cumulative_diff": -4.569999999999999951150186916
        },
        {
            "epoch": 287,
            "expected": 0.59,
            "actual": 0,
            "pool_stake": 632438828557,
            "total_stake": 23041097075076811,
            "decentralisation_coefficient": 0,
            "slot_coefficient": 0.05,
            "cumulative_expected_blocks": 11.15999999999999992006394222,
            "cumulative_actual_blocks": 6,
            "epoch_diff": -0.5899999999999999689137553105,
            "epoch_cumulative_diff": -5.159999999999999920063942226
        },
        {
            "epoch": 288,
            "expected": 0.61,
            "actual": 0,
            "pool_stake": 651276778347,
            "total_stake": 23136223153988390,
            "decentralisation_coefficient": 0,
            "slot_coefficient": 0.05,
            "cumulative_expected_blocks": 11.76999999999999990674126592,
            "cumulative_actual_blocks": 6,
            "epoch_diff": -0.6099999999999999866773237045,
            "epoch_cumulative_diff": -5.769999999999999906741265930
        },
        {
            "epoch": 289,
            "expected": 0.62,
            "actual": 1,
            "pool_stake": 665983399860,
            "total_stake": 23311196777534712,
            "decentralisation_coefficient": 0,
            "slot_coefficient": 0.05,
            "cumulative_expected_blocks": 12.38999999999999990230037382,
            "cumulative_actual_blocks": 7,
            "epoch_diff": 0.3800000000000000044408920985,
            "epoch_cumulative_diff": -5.389999999999999902300373832
        },
        {
            "epoch": 290,
            "expected": 0.63,
            "actual": 1,
            "pool_stake": 678897575934,
            "total_stake": 23253494675755279,
            "decentralisation_coefficient": 0,
            "slot_coefficient": 0.05,
            "cumulative_expected_blocks": 13.01999999999999990674126592,
            "cumulative_actual_blocks": 8,
            "epoch_diff": 0.3699999999999999955591079015,
            "epoch_cumulative_diff": -5.019999999999999906741265930
        },
        {
            "epoch": 291,
            "expected": 0.64,
            "actual": 0,
            "pool_stake": 688177351149,
            "total_stake": 23219858534473043,
            "decentralisation_coefficient": 0,
            "slot_coefficient": 0.05,
            "cumulative_expected_blocks": 13.65999999999999992006394222,
            "cumulative_actual_blocks": 8,
            "epoch_diff": -0.6400000000000000133226762955,
            "epoch_cumulative_diff": -5.659999999999999920063942226
        },
        {
            "epoch": 292,
            "expected": 0.67,
            "actual": 0,
            "pool_stake": 718491374740,
            "total_stake": 23325839206372436,
            "decentralisation_coefficient": 0,
            "slot_coefficient": 0.05,
            "cumulative_expected_blocks": 14.32999999999999996003197111,
            "cumulative_actual_blocks": 8,
            "epoch_diff": -0.6700000000000000399680288865,
            "epoch_cumulative_diff": -6.329999999999999960031971112
        },
        {
            "epoch": 293,
            "expected": 0.67,
            "actual": 1,
            "pool_stake": 721272933936,
            "total_stake": 23395112387185878,
            "decentralisation_coefficient": 0,
            "slot_coefficient": 0.05,
            "cumulative_expected_blocks": 15.00000000000000000000000000,
            "cumulative_actual_blocks": 9,
            "epoch_diff": 0.3299999999999999600319711135,
            "epoch_cumulative_diff": -5.999999999999999999999999998
        },
        {
            "epoch": 294,
            "expected": 0.7,
            "actual": 2,
            "pool_stake": 752485937721,
            "total_stake": 23382668673546580,
            "decentralisation_coefficient": 0,
            "slot_coefficient": 0.05,
            "cumulative_expected_blocks": 15.69999999999999995559107901,
            "cumulative_actual_blocks": 11,
            "epoch_diff": 1.300000000000000044408920985,
            "epoch_cumulative_diff": -4.699999999999999955591079013
        },
        {
            "epoch": 295,
            "expected": 0.7,
            "actual": 1,
            "pool_stake": 756434177204,
            "total_stake": 23411124422164299,
            "decentralisation_coefficient": 0,
            "slot_coefficient": 0.05,
            "cumulative_expected_blocks": 16.39999999999999991118215802,
            "cumulative_actual_blocks": 12,
            "epoch_diff": 0.3000000000000000444089209850,
            "epoch_cumulative_diff": -4.399999999999999911182158028
        },
        {
            "epoch": 296,
            "expected": 0.68,
            "actual": 0,
            "pool_stake": 741482227399,
            "total_stake": 23445774697795279,
            "decentralisation_coefficient": 0,
            "slot_coefficient": 0.05,
            "cumulative_expected_blocks": 17.07999999999999996003197110,
            "cumulative_actual_blocks": 12,
            "epoch_diff": -0.6800000000000000488498130835,
            "epoch_cumulative_diff": -5.079999999999999960031971112
        },
        {
            "epoch": 297,
            "expected": 0.68,
            "actual": 2,
            "pool_stake": 733844514258,
            "total_stake": 23478023193513019,
            "decentralisation_coefficient": 0,
            "slot_coefficient": 0.05,
            "cumulative_expected_blocks": 17.76000000000000000888178418,
            "cumulative_actual_blocks": 14,
            "epoch_diff": 1.319999999999999951150186916,
            "epoch_cumulative_diff": -3.760000000000000008881784196
        },
        {
            "epoch": 298,
            "expected": 0.68,
            "actual": 1,
            "pool_stake": 738594373019,
            "total_stake": 23511990337865722,
            "decentralisation_coefficient": 0,
            "slot_coefficient": 0.05,
            "cumulative_expected_blocks": 18.44000000000000005773159726,
            "cumulative_actual_blocks": 15,
            "epoch_diff": 0.3199999999999999511501869165,
            "epoch_cumulative_diff": -3.440000000000000057731597280
        },
        {
            "epoch": 299,
            "expected": 0.68,
            "actual": 1,
            "pool_stake": 737546611103,
            "total_stake": 23564534162883159,
            "decentralisation_coefficient": 0,
            "slot_coefficient": 0.05,
            "cumulative_expected_blocks": 19.12000000000000010658141034,
            "cumulative_actual_blocks": 16,
            "epoch_diff": 0.3199999999999999511501869165,
            "epoch_cumulative_diff": -3.120000000000000106581410364
        },
        {
            "epoch": 300,
            "expected": 0.67,
            "actual": 1,
            "pool_stake": 736670278877,
            "total_stake": 23882888816746304,
            "decentralisation_coefficient": 0,
            "slot_coefficient": 0.05,
            "cumulative_expected_blocks": 19.79000000000000014654943923,
            "cumulative_actual_blocks": 17,
            "epoch_diff": 0.3299999999999999600319711135,
            "epoch_cumulative_diff": -2.790000000000000146549439250
        },
        {
            "epoch": 301,
            "expected": 0.67,
            "actual": 0,
            "pool_stake": 739275081481,
            "total_stake": 23857504839454979,
            "decentralisation_coefficient": 0,
            "slot_coefficient": 0.05,
            "cumulative_expected_blocks": 20.46000000000000018651746812,
            "cumulative_actual_blocks": 17,
            "epoch_diff": -0.6700000000000000399680288865,
            "epoch_cumulative_diff": -3.460000000000000186517468136
        },
        {
            "epoch": 302,
            "expected": 0.72,
            "actual": 0,
            "pool_stake": 798099234035,
            "total_stake": 23848572589189307,
            "decentralisation_coefficient": 0,
            "slot_coefficient": 0.05,
            "cumulative_expected_blocks": 21.18000000000000015987211553,
            "cumulative_actual_blocks": 17,
            "epoch_diff": -0.7199999999999999733546474090,
            "epoch_cumulative_diff": -4.180000000000000159872115545
        },
        {
            "epoch": 303,
            "expected": 0.73,
            "actual": 1,
            "pool_stake": 802885303032,
            "total_stake": 23849267970809683,
            "decentralisation_coefficient": 0,
            "slot_coefficient": 0.05,
            "cumulative_expected_blocks": 21.91000000000000014210854714,
            "cumulative_actual_blocks": 18,
            "epoch_diff": 0.2700000000000000177635683940,
            "epoch_cumulative_diff": -3.910000000000000142108547151
        },
        {
            "epoch": 304,
            "expected": 0.73,
            "actual": 0,
            "pool_stake": 806209895152,
            "total_stake": 23856125875170714,
            "decentralisation_coefficient": 0,
            "slot_coefficient": 0.05,
            "cumulative_expected_blocks": 22.64000000000000012434497875,
            "cumulative_actual_blocks": 18,
            "epoch_diff": -0.7299999999999999822364316060,
            "epoch_cumulative_diff": -4.640000000000000124344978757
        },
        {
            "epoch": 305,
            "expected": 0.74,
            "actual": 0,
            "pool_stake": 814470778591,
            "total_stake": 23854747611964258,
            "decentralisation_coefficient": 0,
            "slot_coefficient": 0.05,
            "cumulative_expected_blocks": 23.38000000000000011546319455,
            "cumulative_actual_blocks": 18,
            "epoch_diff": -0.7399999999999999911182158030,
            "epoch_cumulative_diff": -5.380000000000000115463194560
        },
        {
            "epoch": 306,
            "expected": 0.73,
            "actual": 0,
            "pool_stake": 811067815928,
            "total_stake": 23836977371261268,
            "decentralisation_coefficient": 0,
            "slot_coefficient": 0.05,
            "cumulative_expected_blocks": 24.11000000000000009769962616,
            "cumulative_actual_blocks": 18,
            "epoch_diff": -0.7299999999999999822364316060,
            "epoch_cumulative_diff": -6.110000000000000097699626166
        },
        {
            "epoch": 307,
            "expected": 0.75,
            "actual": 2,
            "pool_stake": 832213905436,
            "total_stake": 23854464200396318,
            "decentralisation_coefficient": 0,
            "slot_coefficient": 0.05,
            "cumulative_expected_blocks": 24.86000000000000009769962616,
            "cumulative_actual_blocks": 20,
            "epoch_diff": 1.25,
            "epoch_cumulative_diff": -4.860000000000000097699626166
        },
        {
            "epoch": 308,
            "expected": 0.75,
            "actual": 0,
            "pool_stake": 828397796730,
            "total_stake": 23828103259412320,
            "decentralisation_coefficient": 0,
            "slot_coefficient": 0.05,
            "cumulative_expected_blocks": 25.61000000000000009769962616,
            "cumulative_actual_blocks": 20,
            "epoch_diff": -0.75,
            "epoch_cumulative_diff": -5.610000000000000097699626166
        },
        {
            "epoch": 309,
            "expected": 0.75,
            "actual": 0,
            "pool_stake": 829388380197,
            "total_stake": 23765024934948158,
            "decentralisation_coefficient": 0,
            "slot_coefficient": 0.05,
            "cumulative_expected_blocks": 26.36000000000000009769962616,
            "cumulative_actual_blocks": 20,
            "epoch_diff": -0.75,
            "epoch_cumulative_diff": -6.360000000000000097699626166
        },
        {
            "epoch": 310,
            "expected": 0.78,
            "actual": 0,
            "pool_stake": 861419367410,
            "total_stake": 23777625558169828,
            "decentralisation_coefficient": 0,
            "slot_coefficient": 0.05,
            "cumulative_expected_blocks": 27.14000000000000012434497875,
            "cumulative_actual_blocks": 20,
            "epoch_diff": -0.7800000000000000266453525910,
            "epoch_cumulative_diff": -7.140000000000000124344978757
        },
        {
            "epoch": 311,
            "expected": 0.77,
            "actual": 0,
            "pool_stake": 848378475979,
            "total_stake": 23732237106487225,
            "decentralisation_coefficient": 0,
            "slot_coefficient": 0.05,
            "cumulative_expected_blocks": 27.91000000000000014210854714,
            "cumulative_actual_blocks": 20,
            "epoch_diff": -0.7700000000000000177635683940,
            "epoch_cumulative_diff": -7.910000000000000142108547151
        },
        {
            "epoch": 312,
            "expected": 0.75,
            "actual": 1,
            "pool_stake": 826800641734,
            "total_stake": 23741900713307325,
            "decentralisation_coefficient": 0,
            "slot_coefficient": 0.05,
            "cumulative_expected_blocks": 28.66000000000000014210854714,
            "cumulative_actual_blocks": 21,
            "epoch_diff": 0.25,
            "epoch_cumulative_diff": -7.660000000000000142108547151
        },
        {
            "epoch": 313,
            "expected": 0.76,
            "actual": 0,
            "pool_stake": 832842080642,
            "total_stake": 23726880119033853,
            "decentralisation_coefficient": 0,
            "slot_coefficient": 0.05,
            "cumulative_expected_blocks": 29.42000000000000015099033134,
            "cumulative_actual_blocks": 21,
            "epoch_diff": -0.7600000000000000088817841970,
            "epoch_cumulative_diff": -8.420000000000000150990331348
        },
        {
            "epoch": 314,
            "expected": 0.74,
            "actual": 1,
            "pool_stake": 813293973298,
            "total_stake": 23604987896132501,
            "decentralisation_coefficient": 0,
            "slot_coefficient": 0.05,
            "cumulative_expected_blocks": 30.16000000000000014210854714,
            "cumulative_actual_blocks": 22,
            "epoch_diff": 0.2600000000000000088817841970,
            "epoch_cumulative_diff": -8.160000000000000142108547151
        },
        {
            "epoch": 315,
            "expected": 0.74,
            "actual": 2,
            "pool_stake": 809855133110,
            "total_stake": 23537012833083860,
            "decentralisation_coefficient": 0,
            "slot_coefficient": 0.05,
            "cumulative_expected_blocks": 30.90000000000000013322676294,
            "cumulative_actual_blocks": 24,
            "epoch_diff": 1.260000000000000008881784197,
            "epoch_cumulative_diff": -6.900000000000000133226762954
        },
        {
            "epoch": 316,
            "expected": 0.75,
            "actual": 2,
            "pool_stake": 814009547155,
            "total_stake": 23549369658121787,
            "decentralisation_coefficient": 0,
            "slot_coefficient": 0.05,
            "cumulative_expected_blocks": 31.65000000000000013322676294,
            "cumulative_actual_blocks": 26,
            "epoch_diff": 1.25,
            "epoch_cumulative_diff": -5.650000000000000133226762954
        },
        {
            "epoch": 317,
            "expected": 0.68,
            "actual": 0,
            "pool_stake": 740449022794,
            "total_stake": 23582836244979864,
            "decentralisation_coefficient": 0,
            "slot_coefficient": 0.05,
            "cumulative_expected_blocks": 32.33000000000000018207657602,
            "cumulative_actual_blocks": 26,
            "epoch_diff": -0.6800000000000000488498130835,
            "epoch_cumulative_diff": -6.330000000000000182076576038
        },
        {
            "epoch": 318,
            "expected": 0.67,
            "actual": 0,
            "pool_stake": 730223063263,
            "total_stake": 23583277486361153,
            "decentralisation_coefficient": 0,
            "slot_coefficient": 0.05,
            "cumulative_expected_blocks": 33.00000000000000022204460491,
            "cumulative_actual_blocks": 26,
            "epoch_diff": -0.6700000000000000399680288865,
            "epoch_cumulative_diff": -7.000000000000000222044604924
        },
        {
            "epoch": 319,
            "expected": 0.68,
            "actual": 1,
            "pool_stake": 738466695489,
            "total_stake": 23565309681268636,
            "decentralisation_coefficient": 0,
            "slot_coefficient": 0.05,
            "cumulative_expected_blocks": 33.68000000000000027089441799,
            "cumulative_actual_blocks": 27,
            "epoch_diff": 0.3199999999999999511501869165,
            "epoch_cumulative_diff": -6.680000000000000270894418008
        },
        {
            "epoch": 320,
            "expected": 0.68,
            "actual": 2,
            "pool_stake": 744863608840,
            "total_stake": 23561047526582598,
            "decentralisation_coefficient": 0,
            "slot_coefficient": 0.05,
            "cumulative_expected_blocks": 34.36000000000000031974423107,
            "cumulative_actual_blocks": 29,
            "epoch_diff": 1.319999999999999951150186916,
            "epoch_cumulative_diff": -5.360000000000000319744231092
        },
        {
            "epoch": 321,
            "expected": 0.7,
            "actual": 0,
            "pool_stake": 767379749344,
            "total_stake": 23537719498083358,
            "decentralisation_coefficient": 0,
            "slot_coefficient": 0.05,
            "cumulative_expected_blocks": 35.06000000000000027533531008,
            "cumulative_actual_blocks": 29,
            "epoch_diff": -0.6999999999999999555910790150,
            "epoch_cumulative_diff": -6.060000000000000275335310107
        },
        {
            "epoch": 322,
            "expected": 0.72,
            "actual": 0,
            "pool_stake": 781191467206,
            "total_stake": 23504746248174263,
            "decentralisation_coefficient": 0,
            "slot_coefficient": 0.05,
            "cumulative_expected_blocks": 35.78000000000000024868995749,
            "cumulative_actual_blocks": 29,
            "epoch_diff": -0.7199999999999999733546474090,
            "epoch_cumulative_diff": -6.780000000000000248689957516
        },
        {
            "epoch": 323,
            "expected": 0.73,
            "actual": 2,
            "pool_stake": 788932113863,
            "total_stake": 23487356050894396,
            "decentralisation_coefficient": 0,
            "slot_coefficient": 0.05,
            "cumulative_expected_blocks": 36.51000000000000023092638910,
            "cumulative_actual_blocks": 31,
            "epoch_diff": 1.270000000000000017763568394,
            "epoch_cumulative_diff": -5.510000000000000230926389122
        },
        {
            "epoch": 324,
            "expected": 0.74,
            "actual": 0,
            "pool_stake": 798901855402,
            "total_stake": 23354498909628269,
            "decentralisation_coefficient": 0,
            "slot_coefficient": 0.05,
            "cumulative_expected_blocks": 37.25000000000000022204460490,
            "cumulative_actual_blocks": 31,
            "epoch_diff": -0.7399999999999999911182158030,
            "epoch_cumulative_diff": -6.250000000000000222044604925
        },
        {
            "epoch": 325,
            "expected": 0.75,
            "actual": 1,
            "pool_stake": 808489381456,
            "total_stake": 23417671451022013,
            "decentralisation_coefficient": 0,
            "slot_coefficient": 0.05,
            "cumulative_expected_blocks": 38.00000000000000022204460490,
            "cumulative_actual_blocks": 32,
            "epoch_diff": 0.25,
            "epoch_cumulative_diff": -6.000000000000000222044604925
        },
        {
            "epoch": 326,
            "expected": 0.76,
            "actual": 2,
            "pool_stake": 816730788091,
            "total_stake": 23301004853802289,
            "decentralisation_coefficient": 0,
            "slot_coefficient": 0.05,
            "cumulative_expected_blocks": 38.76000000000000023092638910,
            "cumulative_actual_blocks": 34,
            "epoch_diff": 1.239999999999999991118215803,
            "epoch_cumulative_diff": -4.760000000000000230926389122
        },
        {
            "epoch": 327,
            "expected": 0.76,
            "actual": 2,
            "pool_stake": 821039619052,
            "total_stake": 23258804977034064,
            "decentralisation_coefficient": 0,
            "slot_coefficient": 0.05,
            "cumulative_expected_blocks": 39.52000000000000023980817330,
            "cumulative_actual_blocks": 36,
            "epoch_diff": 1.239999999999999991118215803,
            "epoch_cumulative_diff": -3.520000000000000239808173319
        },
        {
            "epoch": 328,
            "expected": 0.77,
            "actual": 1,
            "pool_stake": 824702314721,
            "total_stake": 23216173396125970,
            "decentralisation_coefficient": 0,
            "slot_coefficient": 0.05,
            "cumulative_expected_blocks": 40.29000000000000025757174169,
            "cumulative_actual_blocks": 37,
            "epoch_diff": 0.2299999999999999822364316060,
            "epoch_cumulative_diff": -3.290000000000000257571741713
        },
        {
            "epoch": 329,
            "expected": 0.74,
            "actual": 1,
            "pool_stake": 838223097027,
            "total_stake": 24598636428762437,
            "decentralisation_coefficient": 0,
            "slot_coefficient": 0.05,
            "cumulative_expected_blocks": 41.03000000000000024868995749,
            "cumulative_actual_blocks": 38,
            "epoch_diff": 0.2600000000000000088817841970,
            "epoch_cumulative_diff": -3.030000000000000248689957516
        },
        {
            "epoch": 330,
            "expected": 0.73,
            "actual": 1,
            "pool_stake": 836205725006,
            "total_stake": 24587384093653744,
            "decentralisation_coefficient": 0,
            "slot_coefficient": 0.05,
            "cumulative_expected_blocks": 41.76000000000000023092638910,
            "cumulative_actual_blocks": 39,
            "epoch_diff": 0.2700000000000000177635683940,
            "epoch_cumulative_diff": -2.760000000000000230926389122
        },
        {
            "epoch": 331,
            "expected": 0.74,
            "actual": 1,
            "pool_stake": 840976743118,
            "total_stake": 24665771640296284,
            "decentralisation_coefficient": 0,
            "slot_coefficient": 0.05,
            "cumulative_expected_blocks": 42.50000000000000022204460490,
            "cumulative_actual_blocks": 40,
            "epoch_diff": 0.2600000000000000088817841970,
            "epoch_cumulative_diff": -2.500000000000000222044604925
        },
        {
            "epoch": 332,
            "expected": 0.74,
            "actual": 2,
            "pool_stake": 841897513075,
            "total_stake": 24727842768797003,
            "decentralisation_coefficient": 0,
            "slot_coefficient": 0.05,
            "cumulative_expected_blocks": 43.24000000000000021316282070,
            "cumulative_actual_blocks": 42,
            "epoch_diff": 1.260000000000000008881784197,
            "epoch_cumulative_diff": -1.240000000000000213162820728
        },
        {
            "epoch": 333,
            "expected": 0.73,
            "actual": 2,
            "pool_stake": 840950700399,
            "total_stake": 24714063915931440,
            "decentralisation_coefficient": 0,
            "slot_coefficient": 0.05,
            "cumulative_expected_blocks": 43.97000000000000019539925231,
            "cumulative_actual_blocks": 44,
            "epoch_diff": 1.270000000000000017763568394,
            "epoch_cumulative_diff": 0.029999999999999804600747666
        },
        {
            "epoch": 334,
            "expected": 0.73,
            "actual": 2,
            "pool_stake": 841576903263,
            "total_stake": 24776127551439804,
            "decentralisation_coefficient": 0,
            "slot_coefficient": 0.05,
            "cumulative_expected_blocks": 44.70000000000000017763568392,
            "cumulative_actual_blocks": 46,
            "epoch_diff": 1.270000000000000017763568394,
            "epoch_cumulative_diff": 1.299999999999999822364316060
        },
        {
            "epoch": 335,
            "expected": 0.74,
            "actual": 0,
            "pool_stake": 847644531838,
            "total_stake": 24769119181729635,
            "decentralisation_coefficient": 0,
            "slot_coefficient": 0.05,
            "cumulative_expected_blocks": 45.44000000000000016875389972,
            "cumulative_actual_blocks": 46,
            "epoch_diff": -0.7399999999999999911182158030,
            "epoch_cumulative_diff": 0.5599999999999998312461002570
        },
        {
            "epoch": 336,
            "expected": 0.74,
            "actual": 2,
            "pool_stake": 848745388279,
            "total_stake": 24767062828320552,
            "decentralisation_coefficient": 0,
            "slot_coefficient": 0.05,
            "cumulative_expected_blocks": 46.18000000000000015987211552,
            "cumulative_actual_blocks": 48,
            "epoch_diff": 1.260000000000000008881784197,
            "epoch_cumulative_diff": 1.819999999999999840127884454
        },
        {
            "epoch": 337,
            "expected": 0.74,
            "actual": 1,
            "pool_stake": 852909945444,
            "total_stake": 24753443176758479,
            "decentralisation_coefficient": 0,
            "slot_coefficient": 0.05,
            "cumulative_expected_blocks": 46.92000000000000015099033132,
            "cumulative_actual_blocks": 49,
            "epoch_diff": 0.2600000000000000088817841970,
            "epoch_cumulative_diff": 2.079999999999999849009668651
        },
        {
            "epoch": 338,
            "expected": 0.77,
            "actual": 1,
            "pool_stake": 877963654934,
            "total_stake": 24621517986831382,
            "decentralisation_coefficient": 0,
            "slot_coefficient": 0.05,
            "cumulative_expected_blocks": 47.69000000000000016875389971,
            "cumulative_actual_blocks": 50,
            "epoch_diff": 0.2299999999999999822364316060,
            "epoch_cumulative_diff": 2.309999999999999831246100257
        },
        {
            "epoch": 339,
            "expected": 1.04,
            "actual": 0,
            "pool_stake": 1186998858513,
            "total_stake": 24682659914204521,
            "decentralisation_coefficient": 0,
            "slot_coefficient": 0.05,
            "cumulative_expected_blocks": 48.73000000000000020428103650,
            "cumulative_actual_blocks": 50,
            "epoch_diff": -1.040000000000000035527136788,
            "epoch_cumulative_diff": 1.269999999999999795718963469
        },
        {
            "epoch": 340,
            "expected": 1.06,
            "actual": 1,
            "pool_stake": 1203380409533,
            "total_stake": 24476700813527397,
            "decentralisation_coefficient": 0,
            "slot_coefficient": 0.05,
            "cumulative_expected_blocks": 49.79000000000000025757174168,
            "cumulative_actual_blocks": 51,
            "epoch_diff": -0.06000000000000005329070518201,
            "epoch_cumulative_diff": 1.209999999999999742428258287
        },
        {
            "epoch": 341,
            "expected": 1.09,
            "actual": 0,
            "pool_stake": 1243757926381,
            "total_stake": 24555840771807746,
            "decentralisation_coefficient": 0,
            "slot_coefficient": 0.05,
            "cumulative_expected_blocks": 50.88000000000000033750779945,
            "cumulative_actual_blocks": 51,
            "epoch_diff": -1.090000000000000079936057773,
            "epoch_cumulative_diff": 0.119999999999999662492200514
        },
        {
            "epoch": 342,
            "expected": 1.09,
            "actual": 1,
            "pool_stake": 1248573239420,
            "total_stake": 24660991673767486,
            "decentralisation_coefficient": 0,
            "slot_coefficient": 0.05,
            "cumulative_expected_blocks": 51.97000000000000041744385722,
            "cumulative_actual_blocks": 52,
            "epoch_diff": -0.09000000000000007993605777301,
            "epoch_cumulative_diff": 0.02999999999999958255614274099
        },
        {
            "epoch": 343,
            "expected": 1.1,
            "actual": 1,
            "pool_stake": 1251062812022,
            "total_stake": 24538091587045780,
            "decentralisation_coefficient": 0,
            "slot_coefficient": 0.05,
            "cumulative_expected_blocks": 53.07000000000000050626169919,
            "cumulative_actual_blocks": 53,
            "epoch_diff": -0.1000000000000000888178419700,
            "epoch_cumulative_diff": -0.07000000000000050626169922901
        },
        {
            "epoch": 344,
            "expected": 1.08,
            "actual": 1,
            "pool_stake": 1230383838580,
            "total_stake": 24602095926151255,
            "decentralisation_coefficient": 0,
            "slot_coefficient": 0.05,
            "cumulative_expected_blocks": 54.15000000000000057731597277,
            "cumulative_actual_blocks": 54,
            "epoch_diff": -0.08000000000000007105427357601,
            "epoch_cumulative_diff": -0.1500000000000005773159728050
        },
        {
            "epoch": 345,
            "expected": 0.81,
            "actual": 1,
            "pool_stake": 928790580236,
            "total_stake": 24677704327308250,
            "decentralisation_coefficient": 0,
            "slot_coefficient": 0.05,
            "cumulative_expected_blocks": 54.96000000000000063060667795,
            "cumulative_actual_blocks": 55,
            "epoch_diff": 0.1899999999999999467092948180,
            "epoch_cumulative_diff": 0.0399999999999993693933220130
        },
        {
            "epoch": 346,
            "expected": 0.77,
            "actual": 0,
            "pool_stake": 880291275618,
            "total_stake": 24637590261789712,
            "decentralisation_coefficient": 0,
            "slot_coefficient": 0.05,
            "cumulative_expected_blocks": 55.73000000000000064837024634,
            "cumulative_actual_blocks": 55,
            "epoch_diff": -0.7700000000000000177635683940,
            "epoch_cumulative_diff": -0.7300000000000006483702463810
        },
        {
            "epoch": 347,
            "expected": 0.76,
            "actual": 2,
            "pool_stake": 871795819328,
            "total_stake": 24669825450454874,
            "decentralisation_coefficient": 0,
            "slot_coefficient": 0.05,
            "cumulative_expected_blocks": 56.49000000000000065725203054,
            "cumulative_actual_blocks": 57,
            "epoch_diff": 1.239999999999999991118215803,
            "epoch_cumulative_diff": 0.5099999999999993427479694220
        },
        {
            "epoch": 348,
            "expected": 0.76,
            "actual": 0,
            "pool_stake": 873735479905,
            "total_stake": 24670614381381442,
            "decentralisation_coefficient": 0,
            "slot_coefficient": 0.05,
            "cumulative_expected_blocks": 57.25000000000000066613381474,
            "cumulative_actual_blocks": 57,
            "epoch_diff": -0.7600000000000000088817841970,
            "epoch_cumulative_diff": -0.2500000000000006661338147750
        },
        {
            "epoch": 349,
            "expected": 0.77,
            "actual": 2,
            "pool_stake": 872626727405,
            "total_stake": 24435357519567074,
            "decentralisation_coefficient": 0,
            "slot_coefficient": 0.05,
            "cumulative_expected_blocks": 58.02000000000000068389738313,
            "cumulative_actual_blocks": 59,
            "epoch_diff": 1.229999999999999982236431606,
            "epoch_cumulative_diff": 0.9799999999999993161026168310
        },
        {
            "epoch": 350,
            "expected": 0.77,
            "actual": 2,
            "pool_stake": 870163325983,
            "total_stake": 24444238585047094,
            "decentralisation_coefficient": 0,
            "slot_coefficient": 0.05,
            "cumulative_expected_blocks": 58.79000000000000070166095152,
            "cumulative_actual_blocks": 61,
            "epoch_diff": 1.229999999999999982236431606,
            "epoch_cumulative_diff": 2.209999999999999298339048437
        },
        {
            "epoch": 351,
            "expected": 0.77,
            "actual": 1,
            "pool_stake": 868222293254,
            "total_stake": 24456415918186222,
            "decentralisation_coefficient": 0,
            "slot_coefficient": 0.05,
            "cumulative_expected_blocks": 59.56000000000000071942451991,
            "cumulative_actual_blocks": 62,
            "epoch_diff": 0.2299999999999999822364316060,
            "epoch_cumulative_diff": 2.439999999999999280575480043
        },
        {
            "epoch": 352,
            "expected": 0.77,
            "actual": 0,
            "pool_stake": 871146368343,
            "total_stake": 24441961174746539,
            "decentralisation_coefficient": 0,
            "slot_coefficient": 0.05,
            "cumulative_expected_blocks": 60.33000000000000073718808830,
            "cumulative_actual_blocks": 62,
            "epoch_diff": -0.7700000000000000177635683940,
            "epoch_cumulative_diff": 1.669999999999999262811911649
        },
        {
            "epoch": 353,
            "expected": 0.77,
            "actual": 0,
            "pool_stake": 873009562172,
            "total_stake": 24453012636354912,
            "decentralisation_coefficient": 0,
            "slot_coefficient": 0.05,
            "cumulative_expected_blocks": 61.10000000000000075495165669,
            "cumulative_actual_blocks": 62,
            "epoch_diff": -0.7700000000000000177635683940,
            "epoch_cumulative_diff": 0.8999999999999992450483432550
        },
        {
            "epoch": 354,
            "expected": 0.77,
            "actual": 0,
            "pool_stake": 874195830382,
            "total_stake": 24463445965412728,
            "decentralisation_coefficient": 0,
            "slot_coefficient": 0.05,
            "cumulative_expected_blocks": 61.87000000000000077271522508,
            "cumulative_actual_blocks": 62,
            "epoch_diff": -0.7700000000000000177635683940,
            "epoch_cumulative_diff": 0.1299999999999992272847748610
        },
        {
            "epoch": 355,
            "expected": 0.76,
            "actual": 1,
            "pool_stake": 864581416464,
            "total_stake": 24525857119151547,
            "decentralisation_coefficient": 0,
            "slot_coefficient": 0.05,
            "cumulative_expected_blocks": 62.63000000000000078159700928,
            "cumulative_actual_blocks": 63,
            "epoch_diff": 0.2399999999999999911182158030,
            "epoch_cumulative_diff": 0.3699999999999992184029906640
        },
        {
            "epoch": 356,
            "expected": 0.76,
            "actual": 1,
            "pool_stake": 867293749734,
            "total_stake": 24492895353990404,
            "decentralisation_coefficient": 0,
            "slot_coefficient": 0.05,
            "cumulative_expected_blocks": 63.39000000000000079047879348,
            "cumulative_actual_blocks": 64,
            "epoch_diff": 0.2399999999999999911182158030,
            "epoch_cumulative_diff": 0.6099999999999992095212064670
        },
        {
            "epoch": 357,
            "expected": 0.75,
            "actual": 1,
            "pool_stake": 853908699230,
            "total_stake": 24507422389303698,
            "decentralisation_coefficient": 0,
            "slot_coefficient": 0.05,
            "cumulative_expected_blocks": 64.14000000000000079047879348,
            "cumulative_actual_blocks": 65,
            "epoch_diff": 0.25,
            "epoch_cumulative_diff": 0.8599999999999992095212064670
        },
        {
            "epoch": 358,
            "expected": 0.75,
            "actual": 1,
            "pool_stake": 858069122985,
            "total_stake": 24552945219532238,
            "decentralisation_coefficient": 0,
            "slot_coefficient": 0.05,
            "cumulative_expected_blocks": 64.89000000000000079047879348,
            "cumulative_actual_blocks": 66,
            "epoch_diff": 0.25,
            "epoch_cumulative_diff": 1.109999999999999209521206467
        },
        {
            "epoch": 359,
            "expected": 0.75,
            "actual": 0,
            "pool_stake": 858565645293,
            "total_stake": 24623552540372334,
            "decentralisation_coefficient": 0,
            "slot_coefficient": 0.05,
            "cumulative_expected_blocks": 65.64000000000000079047879348,
            "cumulative_actual_blocks": 66,
            "epoch_diff": -0.75,
            "epoch_cumulative_diff": 0.359999999999999209521206467
        },
        {
            "epoch": 360,
            "expected": 0.75,
            "actual": 0,
            "pool_stake": 858342634584,
            "total_stake": 24636399918286027,
            "decentralisation_coefficient": 0,
            "slot_coefficient": 0.05,
            "cumulative_expected_blocks": 66.39000000000000079047879348,
            "cumulative_actual_blocks": 66,
            "epoch_diff": -0.75,
            "epoch_cumulative_diff": -0.390000000000000790478793533
        },
        {
            "epoch": 361,
            "expected": 0.75,
            "actual": 0,
            "pool_stake": 860126044484,
            "total_stake": 24732308831147809,
            "decentralisation_coefficient": 0,
            "slot_coefficient": 0.05,
            "cumulative_expected_blocks": 67.14000000000000079047879348,
            "cumulative_actual_blocks": 66,
            "epoch_diff": -0.75,
            "epoch_cumulative_diff": -1.140000000000000790478793533
        },
        {
            "epoch": 362,
            "expected": 0.75,
            "actual": 0,
            "pool_stake": 853925039709,
            "total_stake": 24724295922908154,
            "decentralisation_coefficient": 0,
            "slot_coefficient": 0.05,
            "cumulative_expected_blocks": 67.89000000000000079047879348,
            "cumulative_actual_blocks": 66,
            "epoch_diff": -0.75,
            "epoch_cumulative_diff": -1.890000000000000790478793533
        },
        {
            "epoch": 363,
            "expected": 0.74,
            "actual": 0,
            "pool_stake": 854333372999,
            "total_stake": 24782466023480092,
            "decentralisation_coefficient": 0,
            "slot_coefficient": 0.05,
            "cumulative_expected_blocks": 68.63000000000000078159700928,
            "cumulative_actual_blocks": 66,
            "epoch_diff": -0.7399999999999999911182158030,
            "epoch_cumulative_diff": -2.630000000000000781597009336
        },
        {
            "epoch": 364,
            "expected": 0.74,
            "actual": 1,
            "pool_stake": 855801132434,
            "total_stake": 25054390221573067,
            "decentralisation_coefficient": 0,
            "slot_coefficient": 0.05,
            "cumulative_expected_blocks": 69.37000000000000077271522508,
            "cumulative_actual_blocks": 67,
            "epoch_diff": 0.2600000000000000088817841970,
            "epoch_cumulative_diff": -2.370000000000000772715225139
        },
        {
            "epoch": 365,
            "expected": 0.74,
            "actual": 0,
            "pool_stake": 857625268217,
            "total_stake": 25043681533090900,
            "decentralisation_coefficient": 0,
            "slot_coefficient": 0.05,
            "cumulative_expected_blocks": 70.11000000000000076383344088,
            "cumulative_actual_blocks": 67,
            "epoch_diff": -0.7399999999999999911182158030,
            "epoch_cumulative_diff": -3.110000000000000763833440942
        },
        {
            "epoch": 366,
            "expected": 0.76,
            "actual": 2,
            "pool_stake": 876316303322,
            "total_stake": 25028585125722443,
            "decentralisation_coefficient": 0,
            "slot_coefficient": 0.05,
            "cumulative_expected_blocks": 70.87000000000000077271522508,
            "cumulative_actual_blocks": 69,
            "epoch_diff": 1.239999999999999991118215803,
            "epoch_cumulative_diff": -1.870000000000000772715225139
        },
        {
            "epoch": 367,
            "expected": 0.78,
            "actual": 0,
            "pool_stake": 905411540051,
            "total_stake": 25065995673156592,
            "decentralisation_coefficient": 0,
            "slot_coefficient": 0.05,
            "cumulative_expected_blocks": 71.65000000000000079936057767,
            "cumulative_actual_blocks": 69,
            "epoch_diff": -0.7800000000000000266453525910,
            "epoch_cumulative_diff": -2.650000000000000799360577730
        },
        {
            "epoch": 368,
            "expected": 0.76,
            "actual": 2,
            "pool_stake": 886995892227,
            "total_stake": 25069171797357765,
            "decentralisation_coefficient": 0,
            "slot_coefficient": 0.05,
            "cumulative_expected_blocks": 72.41000000000000080824236187,
            "cumulative_actual_blocks": 71,
            "epoch_diff": 1.239999999999999991118215803,
            "epoch_cumulative_diff": -1.410000000000000808242361927
        },
        {
            "epoch": 369,
            "expected": 0.74,
            "actual": 1,
            "pool_stake": 864189312608,
            "total_stake": 25153834365108788,
            "decentralisation_coefficient": 0,
            "slot_coefficient": 0.05,
            "cumulative_expected_blocks": 73.15000000000000079936057767,
            "cumulative_actual_blocks": 72,
            "epoch_diff": 0.2600000000000000088817841970,
            "epoch_cumulative_diff": -1.150000000000000799360577730
        },
        {
            "epoch": 370,
            "expected": 0.81,
            "actual": 1,
            "pool_stake": 946201570568,
            "total_stake": 25170337993638844,
            "decentralisation_coefficient": 0,
            "slot_coefficient": 0.05,
            "cumulative_expected_blocks": 73.96000000000000085265128285,
            "cumulative_actual_blocks": 73,
            "epoch_diff": 0.1899999999999999467092948180,
            "epoch_cumulative_diff": -0.9600000000000008526512829120
        },
        {
            "epoch": 371,
            "expected": 0.82,
            "actual": 4,
            "pool_stake": 950215426223,
            "total_stake": 25107902330817417,
            "decentralisation_coefficient": 0,
            "slot_coefficient": 0.05,
            "cumulative_expected_blocks": 74.78000000000000080380146977,
            "cumulative_actual_blocks": 77,
            "epoch_diff": 3.180000000000000048849813084,
            "epoch_cumulative_diff": 2.219999999999999196198530172
        },
        {
            "epoch": 372,
            "expected": 0.85,
            "actual": 3,
            "pool_stake": 984873724365,
            "total_stake": 25087226705234193,
            "decentralisation_coefficient": 0,
            "slot_coefficient": 0.05,
            "cumulative_expected_blocks": 75.63000000000000078159700928,
            "cumulative_actual_blocks": 80,
            "epoch_diff": 2.150000000000000022204460493,
            "epoch_cumulative_diff": 4.369999999999999218402990665
        },
        {
            "epoch": 373,
            "expected": 1.0,
            "actual": 1,
            "pool_stake": 1157603555180,
            "total_stake": 25090663550263367,
            "decentralisation_coefficient": 0,
            "slot_coefficient": 0.05,
            "cumulative_expected_blocks": 76.63000000000000078159700928,
            "cumulative_actual_blocks": 81,
            "epoch_diff": 0,
            "epoch_cumulative_diff": 4.369999999999999218402990665
        },
        {
            "epoch": 374,
            "expected": 1.02,
            "actual": 1,
            "pool_stake": 1183073867114,
            "total_stake": 25097784395987465,
            "decentralisation_coefficient": 0,
            "slot_coefficient": 0.05,
            "cumulative_expected_blocks": 77.65000000000000079936057767,
            "cumulative_actual_blocks": 82,
            "epoch_diff": -0.02000000000000001776356839400,
            "epoch_cumulative_diff": 4.349999999999999200639422271
        },
        {
            "epoch": 375,
            "expected": 1.16,
            "actual": 0,
            "pool_stake": 1346599192007,
            "total_stake": 25174903471204236,
            "decentralisation_coefficient": 0,
            "slot_coefficient": 0.05,
            "cumulative_expected_blocks": 78.81000000000000071942451990,
            "cumulative_actual_blocks": 82,
            "epoch_diff": -1.159999999999999920063942227,
            "epoch_cumulative_diff": 3.189999999999999280575480044
        },
        {
            "epoch": 376,
            "expected": 1.21,
            "actual": 0,
            "pool_stake": 1413837201070,
            "total_stake": 25272403210023564,
            "decentralisation_coefficient": 0,
            "slot_coefficient": 0.05,
            "cumulative_expected_blocks": 80.02000000000000068389738311,
            "cumulative_actual_blocks": 82,
            "epoch_diff": -1.209999999999999964472863212,
            "epoch_cumulative_diff": 1.979999999999999316102616832
        },
        {
            "epoch": 377,
            "expected": 1.28,
            "actual": 0,
            "pool_stake": 1497627021061,
            "total_stake": 25197315592272395,
            "decentralisation_coefficient": 0,
            "slot_coefficient": 0.05,
            "cumulative_expected_blocks": 81.30000000000000071054273570,
            "cumulative_actual_blocks": 82,
            "epoch_diff": -1.280000000000000026645352591,
            "epoch_cumulative_diff": 0.699999999999999289457264241
        },
        {
            "epoch": 378,
            "expected": 1.37,
            "actual": 1,
            "pool_stake": 1596878032546,
            "total_stake": 25116738054461618,
            "decentralisation_coefficient": 0,
            "slot_coefficient": 0.05,
            "cumulative_expected_blocks": 82.67000000000000081712414606,
            "cumulative_actual_blocks": 83,
            "epoch_diff": -0.3700000000000001065814103640,
            "epoch_cumulative_diff": 0.3299999999999991828758538770
        },
        {
            "epoch": 379,
            "expected": 1.38,
            "actual": 2,
            "pool_stake": 1606243488049,
            "total_stake": 25058875481572529,
            "decentralisation_coefficient": 0,
            "slot_coefficient": 0.05,
            "cumulative_expected_blocks": 84.05000000000000071054273570,
            "cumulative_actual_blocks": 85,
            "epoch_diff": 0.6200000000000001065814103640,
            "epoch_cumulative_diff": 0.9499999999999992894572642410
        },
        {
            "epoch": 380,
            "expected": 1.39,
            "actual": 0,
            "pool_stake": 1610095789573,
            "total_stake": 25065309972207037,
            "decentralisation_coefficient": 0,
            "slot_coefficient": 0.05,
            "cumulative_expected_blocks": 85.44000000000000061284310953,
            "cumulative_actual_blocks": 85,
            "epoch_diff": -1.389999999999999902300373833,
            "epoch_cumulative_diff": -0.4400000000000006128431095920
        },
        {
            "epoch": 381,
            "expected": 2.07,
            "actual": 2,
            "pool_stake": 2407027345853,
            "total_stake": 25090595813788584,
            "decentralisation_coefficient": 0,
            "slot_coefficient": 0.05,
            "cumulative_expected_blocks": 87.51000000000000045297099398,
            "cumulative_actual_blocks": 87,
            "epoch_diff": -0.06999999999999984012788445398,
            "epoch_cumulative_diff": -0.5100000000000004529709940460
        },
        {
            "epoch": 382,
            "expected": 2.02,
            "actual": 1,
            "pool_stake": 2342727144672,
            "total_stake": 25079111896910089,
            "decentralisation_coefficient": 0,
            "slot_coefficient": 0.05,
            "cumulative_expected_blocks": 89.53000000000000047073456237,
            "cumulative_actual_blocks": 88,
            "epoch_diff": -1.020000000000000017763568394,
            "epoch_cumulative_diff": -1.530000000000000470734562440
        },
        {
            "epoch": 383,
            "expected": 1.96,
            "actual": 1,
            "pool_stake": 2291019689170,
            "total_stake": 25226159003727233,
            "decentralisation_coefficient": 0,
            "slot_coefficient": 0.05,
            "cumulative_expected_blocks": 91.49000000000000043520742558,
            "cumulative_actual_blocks": 89,
            "epoch_diff": -0.9599999999999999644728632120,
            "epoch_cumulative_diff": -2.490000000000000435207425652
        },
        {
            "epoch": 384,
            "expected": 1.99,
            "actual": 2,
            "pool_stake": 2342419840430,
            "total_stake": 25363740356767789,
            "decentralisation_coefficient": 0,
            "slot_coefficient": 0.05,
            "cumulative_expected_blocks": 93.48000000000000042632564138,
            "cumulative_actual_blocks": 91,
            "epoch_diff": 0.01000000000000000888178419700,
            "epoch_cumulative_diff": -2.480000000000000426325641455
        },
        {
            "epoch": 385,
            "expected": 2.0,
            "actual": 0,
            "pool_stake": 2355790993596,
            "total_stake": 25388654503848140,
            "decentralisation_coefficient": 0,
            "slot_coefficient": 0.05,
            "cumulative_expected_blocks": 95.48000000000000042632564138,
            "cumulative_actual_blocks": 91,
            "epoch_diff": -2,
            "epoch_cumulative_diff": -4.480000000000000426325641455
        },
        {
            "epoch": 386,
            "expected": 1.94,
            "actual": 5,
            "pool_stake": 2250624066043,
            "total_stake": 25107872285168544,
            "decentralisation_coefficient": 0,
            "slot_coefficient": 0.05,
            "cumulative_expected_blocks": 97.42000000000000037303493620,
            "cumulative_actual_blocks": 96,
            "epoch_diff": 3.060000000000000053290705182,
            "epoch_cumulative_diff": -1.420000000000000373034936273
        },
        {
            "epoch": 387,
            "expected": 1.88,
            "actual": 2,
            "pool_stake": 2213951220607,
            "total_stake": 25418973672435766,
            "decentralisation_coefficient": 0,
            "slot_coefficient": 0.05,
            "cumulative_expected_blocks": 99.30000000000000026645352584,
            "cumulative_actual_blocks": 98,
            "epoch_diff": 0.1200000000000001065814103640,
            "epoch_cumulative_diff": -1.300000000000000266453525909
        },
        {
            "epoch": 388,
            "expected": 1.88,
            "actual": 1,
            "pool_stake": 2213607657954,
            "total_stake": 25427056571856294,
            "decentralisation_coefficient": 0,
            "slot_coefficient": 0.05,
            "cumulative_expected_blocks": 101.1800000000000001598721155,
            "cumulative_actual_blocks": 99,
            "epoch_diff": -0.8799999999999998934185896360,
            "epoch_cumulative_diff": -2.180000000000000159872115545
        }
    ],
    "max_epoch_blocks": 5,
    "latest_epoch_pool_stake": 2213607657954,
    "latest_epoch_total_stake": 25427056571856294,
    "max_positive_diff": 2.01,
    "max_negative_diff": 8.42,
    "max_cumulative_diff": 8.42,
    "cumulative_diff": -2.18,
    "cumulative_expected_blocks": 101.1800000000000001598721155,
    "cumulative_actual_blocks": 99,
    "max_actual_blocks": 5,
    "max_expected_blocks": 2.07,
    "current_lifetime_luck": 97.84542399683731947378182520,
    "highest_lifetime_luck": 101.9865586084206364862858734,
    "lowest_lifetime_luck": 91.67819727218817949526017204
}