{
    "ticker": "DDOS",
    "epochs": [
        {
            "epoch": 341,
            "expected": 0.0154407,
            "actual": 0,
            "pool_stake": 17553595686,
            "total_stake": 24555840771807746,
            "decentralisation_coefficient": 0,
            "slot_coefficient": 0.05,
            "cumulative_expected_blocks": 0.0154407,
            "cumulative_actual_blocks": 0,
            "epoch_diff": -0.0154407,
            "epoch_cumulative_diff": -0.0154407
        },
        {
            "epoch": 342,
            "expected": 0.0542305,
            "actual": 0,
            "pool_stake": 61915431328,
            "total_stake": 24660991673767486,
            "decentralisation_coefficient": 0,
            "slot_coefficient": 0.05,
            "cumulative_expected_blocks": 0.0696712,
            "cumulative_actual_blocks": 0,
            "epoch_diff": -0.0542305,
            "epoch_cumulative_diff": -0.0696712
        },
        {
            "epoch": 343,
            "expected": 0.057362,
            "actual": 0,
            "pool_stake": 65164410421,
            "total_stake": 24538091587045780,
            "decentralisation_coefficient": 0,
            "slot_coefficient": 0.05,
            "cumulative_expected_blocks": 0.127033,
            "cumulative_actual_blocks": 0,
            "epoch_diff": -0.0573620,
            "epoch_cumulative_diff": -0.127033
        },
        {
            "epoch": 344,
            "expected": 0.105108,
            "actual": 0,
            "pool_stake": 119715864906,
            "total_stake": 24602095926151255,
            "decentralisation_coefficient": 0,
            "slot_coefficient": 0.05,
            "cumulative_expected_blocks": 0.232141,
            "cumulative_actual_blocks": 0,
            "epoch_diff": -0.105108,
            "epoch_cumulative_diff": -0.232141
        },
        {
            "epoch": 345,
            "expected": 0.105987,
            "actual": 0,
            "pool_stake": 121088530093,
            "total_stake": 24677704327308250,
            "decentralisation_coefficient": 0,
            "slot_coefficient": 0.05,
            "cumulative_expected_blocks": 0.338128,
            "cumulative_actual_blocks": 0,
            "epoch_diff": -0.105987,
            "epoch_cumulative_diff": -0.338128
        },
        {
            "epoch": 346,
            "expected": 0.118174,
            "actual": 0,
            "pool_stake": 134792194558,
            "total_stake": 24637590261789712,
            "decentralisation_coefficient": 0,
            "slot_coefficient": 0.05,
            "cumulative_expected_blocks": 0.456302,
            "cumulative_actual_blocks": 0,
            "epoch_diff": -0.118174,
            "epoch_cumulative_diff": -0.456302
        },
        {
            "epoch": 347,
            "expected": 0.159648,
            "actual": 0,
            "pool_stake": 182337309447,
            "total_stake": 24669825450454874,
            "decentralisation_coefficient": 0,
            "slot_coefficient": 0.05,
            "cumulative_expected_blocks": 0.615950,
            "cumulative_actual_blocks": 0,
            "epoch_diff": -0.159648,
            "epoch_cumulative_diff": -0.615950
        },
        {
            "epoch": 348,
            "expected": 0.16195,
            "actual": 0,
            "pool_stake": 184972458650,
            "total_stake": 24670614381381442,
            "decentralisation_coefficient": 0,
            "slot_coefficient": 0.05,
            "cumulative_expected_blocks": 0.777900,
            "cumulative_actual_blocks": 0,
            "epoch_diff": -0.161950,
            "epoch_cumulative_diff": -0.777900
        },
        {
            "epoch": 349,
            "expected": 0.171766,
            "actual": 0,
            "pool_stake": 194313469909,
            "total_stake": 24435357519567074,
            "decentralisation_coefficient": 0,
            "slot_coefficient": 0.05,
            "cumulative_expected_blocks": 0.949666,
            "cumulative_actual_blocks": 0,
            "epoch_diff": -0.171766,
            "epoch_cumulative_diff": -0.949666
        },
        {
            "epoch": 350,
            "expected": 0.169598,
            "actual": 0,
            "pool_stake": 191929599340,
            "total_stake": 24444238585047094,
            "decentralisation_coefficient": 0,
            "slot_coefficient": 0.05,
            "cumulative_expected_blocks": 1.11926,
            "cumulative_actual_blocks": 0,
            "epoch_diff": -0.169598,
            "epoch_cumulative_diff": -1.11926
        },
        {
            "epoch": 351,
            "expected": 0.17022,
            "actual": 0,
            "pool_stake": 192730372846,
            "total_stake": 24456415918186222,
            "decentralisation_coefficient": 0,
            "slot_coefficient": 0.05,
            "cumulative_expected_blocks": 1.28948,
            "cumulative_actual_blocks": 0,
            "epoch_diff": -0.170220,
            "epoch_cumulative_diff": -1.28948
        },
        {
            "epoch": 352,
            "expected": 0.169747,
            "actual": 0,
            "pool_stake": 192080967371,
            "total_stake": 24441961174746539,
            "decentralisation_coefficient": 0,
            "slot_coefficient": 0.05,
            "cumulative_expected_blocks": 1.45923,
            "cumulative_actual_blocks": 0,
            "epoch_diff": -0.169747,
            "epoch_cumulative_diff": -1.45923
        },
        {
            "epoch": 353,
            "expected": 0.33701,
            "actual": 0,
            "pool_stake": 381522856506,
            "total_stake": 24453012636354912,
            "decentralisation_coefficient": 0,
            "slot_coefficient": 0.05,
            "cumulative_expected_blocks": 1.79624,
            "cumulative_actual_blocks": 0,
            "epoch_diff": -0.337010,
            "epoch_cumulative_diff": -1.79624
        },
        {
            "epoch": 354,
            "expected": 0.327517,
            "actual": 0,
            "pool_stake": 370935266942,
            "total_stake": 24463445965412728,
            "decentralisation_coefficient": 0,
            "slot_coefficient": 0.05,
            "cumulative_expected_blocks": 2.12376,
            "cumulative_actual_blocks": 0,
            "epoch_diff": -0.327517,
            "epoch_cumulative_diff": -2.12376
        },
        {
            "epoch": 355,
            "expected": 0.342987,
            "actual": 0,
            "pool_stake": 389445378214,
            "total_stake": 24525857119151547,
            "decentralisation_coefficient": 0,
            "slot_coefficient": 0.05,
            "cumulative_expected_blocks": 2.46675,
            "cumulative_actual_blocks": 0,
            "epoch_diff": -0.342987,
            "epoch_cumulative_diff": -2.46675
        },
        {
            "epoch": 356,
            "expected": 0.357407,
            "actual": 0,
            "pool_stake": 405275331992,
            "total_stake": 24492895353990404,
            "decentralisation_coefficient": 0,
            "slot_coefficient": 0.05,
            "cumulative_expected_blocks": 2.82416,
            "cumulative_actual_blocks": 0,
            "epoch_diff": -0.357407,
            "epoch_cumulative_diff": -2.82416
        },
        {
            "epoch": 357,
            "expected": 0.354074,
            "actual": 0,
            "pool_stake": 401732140752,
            "total_stake": 24507422389303698,
            "decentralisation_coefficient": 0,
            "slot_coefficient": 0.05,
            "cumulative_expected_blocks": 3.17823,
            "cumulative_actual_blocks": 0,
            "epoch_diff": -0.354074,
            "epoch_cumulative_diff": -3.17823
        },
        {
            "epoch": 358,
            "expected": 0.330994,
            "actual": 0,
            "pool_stake": 376243484934,
            "total_stake": 24552945219532238,
            "decentralisation_coefficient": 0,
            "slot_coefficient": 0.05,
            "cumulative_expected_blocks": 3.50922,
            "cumulative_actual_blocks": 0,
            "epoch_diff": -0.330994,
            "epoch_cumulative_diff": -3.50922
        },
        {
            "epoch": 359,
            "expected": 0.326471,
            "actual": 0,
            "pool_stake": 372169214936,
            "total_stake": 24623552540372334,
            "decentralisation_coefficient": 0,
            "slot_coefficient": 0.05,
            "cumulative_expected_blocks": 3.83569,
            "cumulative_actual_blocks": 0,
            "epoch_diff": -0.326471,
            "epoch_cumulative_diff": -3.83569
        },
        {
            "epoch": 360,
            "expected": 0.305372,
            "actual": 0,
            "pool_stake": 348299585005,
            "total_stake": 24636399918286027,
            "decentralisation_coefficient": 0,
            "slot_coefficient": 0.05,
            "cumulative_expected_blocks": 4.14106,
            "cumulative_actual_blocks": 0,
            "epoch_diff": -0.305372,
            "epoch_cumulative_diff": -4.14106
        },
        {
            "epoch": 361,
            "expected": 0.274746,
            "actual": 0,
            "pool_stake": 314586517608,
            "total_stake": 24732308831147809,
            "decentralisation_coefficient": 0,
            "slot_coefficient": 0.05,
            "cumulative_expected_blocks": 4.41581,
            "cumulative_actual_blocks": 0,
            "epoch_diff": -0.274746,
            "epoch_cumulative_diff": -4.41581
        },
        {
            "epoch": 362,
            "expected": 0.264371,
            "actual": 0,
            "pool_stake": 302610536971,
            "total_stake": 24724295922908154,
            "decentralisation_coefficient": 0,
            "slot_coefficient": 0.05,
            "cumulative_expected_blocks": 4.68018,
            "cumulative_actual_blocks": 0,
            "epoch_diff": -0.264371,
            "epoch_cumulative_diff": -4.68018
        },
        {
            "epoch": 363,
            "expected": 0.258017,
            "actual": 0,
            "pool_stake": 296031061756,
            "total_stake": 24782466023480092,
            "decentralisation_coefficient": 0,
            "slot_coefficient": 0.05,
            "cumulative_expected_blocks": 4.93820,
            "cumulative_actual_blocks": 0,
            "epoch_diff": -0.258017,
            "epoch_cumulative_diff": -4.93820
        },
        {
            "epoch": 364,
            "expected": 0.2525,
            "actual": 0,
            "pool_stake": 292879972796,
            "total_stake": 25054390221573067,
            "decentralisation_coefficient": 0,
            "slot_coefficient": 0.05,
            "cumulative_expected_blocks": 5.19070,
            "cumulative_actual_blocks": 0,
            "epoch_diff": -0.252500,
            "epoch_cumulative_diff": -5.19070
        },
        {
            "epoch": 365,
            "expected": 0.240473,
            "actual": 0,
            "pool_stake": 278811192368,
            "total_stake": 25043681533090900,
            "decentralisation_coefficient": 0,
            "slot_coefficient": 0.05,
            "cumulative_expected_blocks": 5.43117,
            "cumulative_actual_blocks": 0,
            "epoch_diff": -0.240473,
            "epoch_cumulative_diff": -5.43117
        },
        {
            "epoch": 366,
            "expected": 0.242117,
            "actual": 0,
            "pool_stake": 280547727716,
            "total_stake": 25028585125722443,
            "decentralisation_coefficient": 0,
            "slot_coefficient": 0.05,
            "cumulative_expected_blocks": 5.67329,
            "cumulative_actual_blocks": 0,
            "epoch_diff": -0.242117,
            "epoch_cumulative_diff": -5.67329
        },
        {
            "epoch": 367,
            "expected": 0.246901,
            "actual": 0,
            "pool_stake": 286518653160,
            "total_stake": 25065995673156592,
            "decentralisation_coefficient": 0,
            "slot_coefficient": 0.05,
            "cumulative_expected_blocks": 5.92019,
            "cumulative_actual_blocks": 0,
            "epoch_diff": -0.246901,
            "epoch_cumulative_diff": -5.92019
        },
        {
            "epoch": 368,
            "expected": 0.246908,
            "actual": 0,
            "pool_stake": 286562321946,
            "total_stake": 25069171797357765,
            "decentralisation_coefficient": 0,
            "slot_coefficient": 0.05,
            "cumulative_expected_blocks": 6.16710,
            "cumulative_actual_blocks": 0,
            "epoch_diff": -0.246908,
            "epoch_cumulative_diff": -6.16710
        },
        {
            "epoch": 369,
            "expected": 0.239304,
            "actual": 0,
            "pool_stake": 278676673173,
            "total_stake": 25153834365108788,
            "decentralisation_coefficient": 0,
            "slot_coefficient": 0.05,
            "cumulative_expected_blocks": 6.40640,
            "cumulative_actual_blocks": 0,
            "epoch_diff": -0.239304,
            "epoch_cumulative_diff": -6.40640
        },
        {
            "epoch": 370,
            "expected": 0.235907,
            "actual": 0,
            "pool_stake": 274899867500,
            "total_stake": 25170337993638844,
            "decentralisation_coefficient": 0,
            "slot_coefficient": 0.05,
            "cumulative_expected_blocks": 6.64231,
            "cumulative_actual_blocks": 0,
            "epoch_diff": -0.235907,
            "epoch_cumulative_diff": -6.64231
        },
        {
            "epoch": 371,
            "expected": 0.350402,
            "actual": 0,
            "pool_stake": 407308331470,
            "total_stake": 25107902330817417,
            "decentralisation_coefficient": 0,
            "slot_coefficient": 0.05,
            "cumulative_expected_blocks": 6.99271,
            "cumulative_actual_blocks": 0,
            "epoch_diff": -0.350402,
            "epoch_cumulative_diff": -6.99271
        },
        {
            "epoch": 372,
            "expected": 0.473777,
            "actual": 0,
            "pool_stake": 550266011819,
            "total_stake": 25087226705234193,
            "decentralisation_coefficient": 0,
            "slot_coefficient": 0.05,
            "cumulative_expected_blocks": 7.46649,
            "cumulative_actual_blocks": 0,
            "epoch_diff": -0.473777,
            "epoch_cumulative_diff": -7.46649
        },
        {
            "epoch": 373,
            "expected": 0.481307,
            "actual": 1,
            "pool_stake": 559088473805,
            "total_stake": 25090663550263367,
            "decentralisation_coefficient": 0,
            "slot_coefficient": 0.05,
            "cumulative_expected_blocks": 7.94780,
            "cumulative_actual_blocks": 1,
            "epoch_diff": 0.518693,
            "epoch_cumulative_diff": -6.94780
        },
        {
            "epoch": 374,
            "expected": 0.49655,
            "actual": 1,
            "pool_stake": 576958286284,
            "total_stake": 25097784395987465,
            "decentralisation_coefficient": 0,
            "slot_coefficient": 0.05,
            "cumulative_expected_blocks": 8.44435,
            "cumulative_actual_blocks": 2,
            "epoch_diff": 0.503450,
            "epoch_cumulative_diff": -6.44435
        },
        {
            "epoch": 375,
            "expected": 0.54664,
            "actual": 1,
            "pool_stake": 637114172594,
            "total_stake": 25174903471204236,
            "decentralisation_coefficient": 0,
            "slot_coefficient": 0.05,
            "cumulative_expected_blocks": 8.99099,
            "cumulative_actual_blocks": 3,
            "epoch_diff": 0.453360,
            "epoch_cumulative_diff": -5.99099
        },
        {
            "epoch": 376,
            "expected": 0.521205,
            "actual": 1,
            "pool_stake": 609819225011,
            "total_stake": 25272403210023564,
            "decentralisation_coefficient": 0,
            "slot_coefficient": 0.05,
            "cumulative_expected_blocks": 9.51220,
            "cumulative_actual_blocks": 4,
            "epoch_diff": 0.478795,
            "epoch_cumulative_diff": -5.51220
        },
        {
            "epoch": 377,
            "expected": 0.536665,
            "actual": 2,
            "pool_stake": 626046025076,
            "total_stake": 25197315592272395,
            "decentralisation_coefficient": 0,
            "slot_coefficient": 0.05,
            "cumulative_expected_blocks": 10.0489,
            "cumulative_actual_blocks": 6,
            "epoch_diff": 1.46334,
            "epoch_cumulative_diff": -4.04886
        },
        {
            "epoch": 378,
            "expected": 0.56543,
            "actual": 1,
            "pool_stake": 657491080657,
            "total_stake": 25116738054461618,
            "decentralisation_coefficient": 0,
            "slot_coefficient": 0.05,
            "cumulative_expected_blocks": 10.6143,
            "cumulative_actual_blocks": 7,
            "epoch_diff": 0.434570,
            "epoch_cumulative_diff": -3.61429
        },
        {
            "epoch": 379,
            "expected": 0.55035,
            "actual": 1,
            "pool_stake": 638476665065,
            "total_stake": 25058875481572529,
            "decentralisation_coefficient": 0,
            "slot_coefficient": 0.05,
            "cumulative_expected_blocks": 11.1647,
            "cumulative_actual_blocks": 8,
            "epoch_diff": 0.449650,
            "epoch_cumulative_diff": -3.16464
        },
        {
            "epoch": 380,
            "expected": 0.602965,
            "actual": 0,
            "pool_stake": 699701328724,
            "total_stake": 25065309972207037,
            "decentralisation_coefficient": 0,
            "slot_coefficient": 0.05,
            "cumulative_expected_blocks": 11.7677,
            "cumulative_actual_blocks": 8,
            "epoch_diff": -0.602965,
            "epoch_cumulative_diff": -3.76760
        }
    ],
    "max_positive_diff": 0,
    "max_negative_diff": 7.46649,
    "cumulative_diff": -3.76760,
    "cumulative_expected_blocks": 11.7677,
    "cumulative_actual_blocks": 8,
    "max_actual_blocks": 2,
    "max_expected_blocks": 0.602965,
    "current_lifetime_luck": 67.9827,
    "max_epoch_blocks": 2,
    "max_cumulative_diff": 7.46649,
    "highest_lifetime_luck": 100,
    "lowest_lifetime_luck": 36.5510
}